turta_protohat/Turta_Analog.py
turta_protohat/__init__.py
turta_protohat-1.0.0.dist-info/LICENSE
turta_protohat-1.0.0.dist-info/METADATA
turta_protohat-1.0.0.dist-info/WHEEL
turta_protohat-1.0.0.dist-info/top_level.txt
turta_protohat-1.0.0.dist-info/RECORD
